icon_to_image-0.1.6.dist-info/METADATA
icon_to_image-0.1.6.dist-info/WHEEL
icon_to_image-0.1.6.dist-info/entry_points.txt
icon_to_image-0.1.6.dist-info/licenses/LICENSE
icon_to_image/__init__.py
icon_to_image/_native.cp313-win_amd64.pyd
icon_to_image/icon_to_image.pyi
icon_to_image-0.1.6.dist-info/RECORD
