Metadata-Version: 2.4
Name: icon-to-image
Version: 0.1.6
Classifier: Development Status :: 4 - Beta
Classifier: Intended Audience :: Developers
Classifier: License :: OSI Approved :: MIT License
Classifier: Programming Language :: Python :: 3
Classifier: Programming Language :: Python :: 3.10
Classifier: Programming Language :: Python :: 3.11
Classifier: Programming Language :: Python :: 3.12
Classifier: Programming Language :: Python :: 3.13
Classifier: Programming Language :: Python :: 3.14
Classifier: Programming Language :: Rust
Classifier: Topic :: Multimedia :: Graphics
Requires-Dist: pytest>=7.0 ; extra == 'dev'
Requires-Dist: pillow>=9.0 ; extra == 'dev'
Provides-Extra: dev
License-File: LICENSE
Summary: Fast and high quality Font Awesome icon to image renderer
Keywords: fontawesome,icon,image,rendering,rust
Author-email: Max Woolf <max@minimaxir.com>
License: MIT
Requires-Python: >=3.10, <3.15
Project-URL: Homepage, https://github.com/minimaxir/icon-to-image
